activeml/__init__.py
activeml/streamlit_app.py
activeml/data/__init__.py
activeml/data/dataprocessview.py
activeml/eda/__init__.py
activeml/eda/edacustomplot.py
activeml/eda/edamapview.py
activeml/ml/__init__.py
activeml/ml/mlsupervised.py
activeml/utils/__init__.py
activeml/utils/commonutil.py
activeml/utils/maputil.py
activeml/utils/viewutil.py
activeml-0.0.1.dist-info/LICENSE
activeml-0.0.1.dist-info/METADATA
activeml-0.0.1.dist-info/WHEEL
activeml-0.0.1.dist-info/top_level.txt
activeml-0.0.1.dist-info/RECORD
