Metadata-Version: 2.1
Name: activeml
Version: 0.0.1
Summary: A streamlit app for visual data anlysis, processing and machine learning
Home-page: https://github.com/zakariachowdhury/activeml
Author: Zakaria Chowdhury
Author-email: info@zakariachowdhury.com
License: UNKNOWN
Platform: UNKNOWN
Classifier: Programming Language :: Python :: 3
Classifier: License :: OSI Approved :: Apache Software License
Classifier: Operating System :: OS Independent
Requires-Python: >=3.6
